diptox/__init__.py
diptox/chem_processor.py
diptox/cli.py
diptox/core.py
diptox/data_deduplicator.py
diptox/data_io.py
diptox/logger.py
diptox/salts.smi
diptox/solvents.smi
diptox/substructure_search.py
diptox/unit_processor.py
diptox/user_reg.py
diptox/web_request.py
diptox/web_ui.py
diptox-1.0.0.dist-info/licenses/LICENSE
diptox-1.0.0.dist-info/METADATA
diptox-1.0.0.dist-info/WHEEL
diptox-1.0.0.dist-info/entry_points.txt
diptox-1.0.0.dist-info/top_level.txt
diptox-1.0.0.dist-info/RECORD
