Metadata-Version: 2.4
Name: diptox
Version: 1.0.0
Summary: Data Integration and Processing for Computational Toxicology
Author-email: Guijia Bi <gjbi@mail.dlut.edu.cn>
License-Expression: Apache-2.0
Classifier: Development Status :: 4 - Beta
Classifier: Intended Audience :: Science/Research
Classifier: Intended Audience :: Healthcare Industry
Classifier: Topic :: Scientific/Engineering :: Chemistry
Classifier: Topic :: Scientific/Engineering :: Bio-Informatics
Classifier: Programming Language :: Python :: 3
Classifier: Programming Language :: Python :: 3.8
Classifier: Programming Language :: Python :: 3.9
Classifier: Programming Language :: Python :: 3.10
Classifier: Programming Language :: Python :: 3.11
Classifier: Operating System :: OS Independent
Requires-Python: >=3.8
License-File: LICENSE
Requires-Dist: requests
Requires-Dist: rdkit>=2023.3
Requires-Dist: tqdm
Requires-Dist: scipy
Requires-Dist: openpyxl
Requires-Dist: streamlit>=1.0.0
Dynamic: license-file
